maxcord_cli/__init__.py
maxcord_cli/cog_template.py
maxcord_cli/main.py
maxcord_cli/main_template.py
maxcord_cli-0.0.1.dist-info/LICENCE
maxcord_cli-0.0.1.dist-info/METADATA
maxcord_cli-0.0.1.dist-info/WHEEL
maxcord_cli-0.0.1.dist-info/entry_points.txt
maxcord_cli-0.0.1.dist-info/top_level.txt
maxcord_cli-0.0.1.dist-info/RECORD
